rensha256/__init__.py
rensha256/__main__.py
rensha256/rensha256.py
rensha256-0.1.78.dist-info/LICENSE
rensha256-0.1.78.dist-info/METADATA
rensha256-0.1.78.dist-info/WHEEL
rensha256-0.1.78.dist-info/entry_points.txt
rensha256-0.1.78.dist-info/top_level.txt
rensha256-0.1.78.dist-info/RECORD
