Metadata-Version: 1.2
Name: rensha256
Version: 0.1.78
Summary: Python command line application bare bones template.
Home-page: UNKNOWN
Author: Taylor Monacelli
Author-email: taylormonacelli@gmail.com
License: UNKNOWN
Project-URL: Bug Tracker, https://github.com/taylormonacelli/rensha256/issues
Project-URL: Documentation, https://github.com/taylormonacelli/rensha256
Project-URL: Source Code, https://github.com/taylormonacelli/rensha256
Platform: UNKNOWN
Classifier: Programming Language :: Python :: 3
Classifier: License :: OSI Approved :: MIT License
Classifier: Operating System :: OS Independent
Requires-Python: >=3.7
